{
  "props": {
    "value": {
      "type": "Number",
      "desc": "Model of the component defining the split ratio (0.0 < x < 100.0) beetween panes; Either use this property (along with a listener for 'input' event) OR use v-model directive",
      "examples": [ "v-model=\"ratio\"" ]
    },

    "horizontal": {
      "type": "Boolean",
      "desc": "Allows the splitter to split its two panes horizontally, instead of vertically"
    },

    "limits": {
      "type": "Array",
      "desc": "An array of two values representing a ratio of minimum and maximum split area of the two panes (0.0 < x < 100.0)",
      "default": "[10, 90]",
      "examples": [ ":limits=\"[30, 70]\"" ]
    },

    "disable": {
      "extends": "disable"
    },

    "separator-class": {
      "type": [ "Array", "String", "Object" ],
      "desc": "Class definitions to be attributed to the splitter separator",
      "examples": [
        "bg-deep-orange",
        ":separator-class=\"{ 'my-special-class': <condition> }\""
      ]
    },

    "separator-style": {
      "type": [ "Array", "String", "Object" ],
      "desc": "Style definitions to be attributed to the splitter separator",
      "examples": [
        "background-color: #ff0000",
        ":separator-style=\"{ backgroundColor: '#ff0000' }\""
      ]
    }
  },

  "slots": {
    "default": {
      "desc": "Default slot in the devland unslotted content of the component; Suggestion: QTooltip, QMenu"
    },

    "before": {
      "desc": "Content of the pane on left/top"
    },

    "after": {
      "desc": "Content of the pane on right/bottom"
    }
  },

  "events": {
    "input": {
      "desc": "Emitted when component's model value changes; Is also used by v-model",
      "params": {
        "value": {
          "type": "Number",
          "desc": "New model value (0.0 < x < 100.0) defining the ratio between panes",
          "examples": [ 0.22 ]
        }
      }
    }
  }
}
